dollarwave/__init__.py
dollarwave/calculate.py
dollarwave/calculateGUI.py
dollarwave/core.py
dollarwave/assets/adjusted_value_gui_img.png
dollarwave/assets/current_year_change_gui_img.png
dollarwave/assets/dollar_comp_gui_img.png
dollarwave/assets/dollarwave_logo.png
dollarwave/assets/dollarwave_logo_2.png
dollarwave/assets/icon.ico
dollarwave/assets/icon.png
dollarwave/assets/py_dollarwave_logo.png
dollarwave/assets/py_dollarwave_logo_nobg.png
dollarwave/assets/py_dollarwave_logo_nobg_a94_icon.ico
dollarwave-2.0.6.dist-info/METADATA
dollarwave-2.0.6.dist-info/WHEEL
dollarwave-2.0.6.dist-info/top_level.txt
dollarwave-2.0.6.dist-info/RECORD
