Metadata-Version: 2.1
Name: dollarwave
Version: 2.0.6
Summary: ⚠️ DEPRECATED: This package is no longer maintained. Please use quantsumore instead. A comprehensive Python library for scraping and retrieving real-time data across multiple financial markets, including cryptocurrencies, equities, Forex, treasury yields, and consumer price index (CPI) data.
Home-page: https://github.com/cedricmoorejr/dollarwave/tree/v2.0.6
Author: Cedric Moore Jr.
Author-email: cedricmoorejunior5@gmail.com
License: MIT
Project-URL: Source Code, https://github.com/cedricmoorejr/dollarwave/releases/tag/v2.0.6
Project-URL: New Library, https://pypi.org/project/quantsumore
Classifier: Programming Language :: Python :: 3
Classifier: License :: OSI Approved :: MIT License
Classifier: Operating System :: Microsoft :: Windows
Classifier: Operating System :: POSIX :: Linux
Classifier: Operating System :: MacOS :: MacOS X
Classifier: Development Status :: 7 - Inactive
Classifier: Intended Audience :: Developers
Classifier: Natural Language :: English
Classifier: Programming Language :: Python :: 3.8
Classifier: Programming Language :: Python :: 3.9
Classifier: Programming Language :: Python :: 3.10
Requires-Python: >=3.6
Requires-Dist: pandas
Requires-Dist: requests
Requires-Dist: matplotlib
Requires-Dist: pillow
